lets_debug/__init__.py
lets_debug/decorator_tools.py
lets_debug/terminal.py
lets_debug-0.0.4.dist-info/LICENSE
lets_debug-0.0.4.dist-info/METADATA
lets_debug-0.0.4.dist-info/WHEEL
lets_debug-0.0.4.dist-info/top_level.txt
lets_debug-0.0.4.dist-info/RECORD
