Metadata-Version: 2.1
Name: lets-debug
Version: 0.0.4
Summary: Useful tools for debugging Python code
Home-page: https://github.com/luizfilipezs/lets-debug
Author: Luiz Filipe da Silva
Author-email: filipeluiz.bs@gmail.com
License: MIT License
Keywords: debug tools terminal
Platform: UNKNOWN
Requires-Python: >=3.7.5
